2Keys-0.5.1.dist-info/DESCRIPTION.rst
2Keys-0.5.1.dist-info/METADATA
2Keys-0.5.1.dist-info/RECORD
2Keys-0.5.1.dist-info/WHEEL
2Keys-0.5.1.dist-info/entry_points.txt
2Keys-0.5.1.dist-info/metadata.json
2Keys-0.5.1.dist-info/top_level.txt
tests/__init__.py
tests/test_util.py
twokeys/__init__.py
twokeys/__main__.py
twokeys/add_keyboard/__init__.py
twokeys/add_keyboard/add_keyboard.py
twokeys/add_keyboard/async_handler.py
twokeys/add_keyboard/sync_keyboard_path.py
twokeys/assets/register.sh
twokeys/assets/service.service
twokeys/cli/__init__.py
twokeys/cli/cli.py
twokeys/daemon/__init__.py
twokeys/daemon/scripts.py
twokeys/init/__init__.py
twokeys/init/init.py
twokeys/sync/__init__.py
twokeys/sync/resync_config.py
twokeys/util/__init__.py
twokeys/util/config.py
twokeys/util/constants.py
twokeys/util/keyboard_map.py
twokeys/util/logger.py
twokeys/watcher/__init__.py
twokeys/watcher/watch_keyboard.py
