Metadata-Version: 2.0
Name: 2Keys
Version: 0.5.1
Summary: A easy to setup second keyboard, designed for everyone. 
Home-page: https://github.com/Gum-Joe/2Keys
Author: Gum-Joe
Author-email: kishansambhi@hotmail.co.uk
License: GPLv3
Keywords: hid ahk autohotkey macros 2cdkeyboard keyboards
Platform: UNKNOWN
Classifier: Development Status :: 2 - Pre-Alpha
Classifier: Operating System :: POSIX :: Linux
Classifier: Programming Language :: Python :: 3.5
Classifier: License :: OSI Approved :: GNU General Public License v3 (GPLv3)
Requires-Dist: aiofiles (==0.4.0)
Requires-Dist: aiohttp (==3.6.2)
Requires-Dist: async-timeout (==3.0.1)
Requires-Dist: attrs (==19.3.0)
Requires-Dist: certifi (==2020.4.5.1)
Requires-Dist: chardet (==3.0.4)
Requires-Dist: click (==7.1.1)
Requires-Dist: colorful
Requires-Dist: colorful (==0.5.4)
Requires-Dist: evdev (==1.3.0)
Requires-Dist: idna (==2.9)
Requires-Dist: idna-ssl (==1.1.0)
Requires-Dist: multidict (==4.7.5)
Requires-Dist: pystache (==0.5.4)
Requires-Dist: pyyaml (==5.3.1)
Requires-Dist: requests (==2.23.0)
Requires-Dist: typing-extensions (==3.7.4.2)
Requires-Dist: urllib3 (==1.25.8)
Requires-Dist: yarl (==1.4.2)
